MANIFEST.in
README.rst
requirements
setup.cfg
setup.py
githublabelscopy/__init__.py
githublabelscopy/githublabelscopy.py
githublabelscopy/labels.py
githublabelscopy.egg-info/PKG-INFO
githublabelscopy.egg-info/SOURCES.txt
githublabelscopy.egg-info/dependency_links.txt
githublabelscopy.egg-info/entry_points.txt
githublabelscopy.egg-info/requires.txt
githublabelscopy.egg-info/top_level.txt
githublabelscopy.egg-info/zip-safe