Metadata-Version: 1.1
Name: githublabelscopy
Version: 1.1.0
Summary: A tool to copy labels between repositories using Github API
Home-page: http://github.com/fpietka/github-labels-copy
Author: François Pietka
Author-email: francois@pietka.fr
License: MIT
Platform: UNKNOWN
Classifier: Intended Audience :: Developers
Classifier: License :: OSI Approved :: MIT License
Classifier: Environment :: Console
Classifier: Programming Language :: Python
Classifier: Programming Language :: Python :: 2.6
Classifier: Programming Language :: Python :: 2.7
Classifier: Programming Language :: Python :: 3
Classifier: Programming Language :: Python :: 3.3
Classifier: Programming Language :: Python :: 3.4
Classifier: Programming Language :: Python :: 3.5
Classifier: Programming Language :: Python :: 3.6
